rescrap/__init__.py
rescrap/dict_reg.py
rescrap/rescrap.py
rescrap/rescrapfile.py
rescrap/rescrapweb.py
rescrap-0.1.2.dist-info/WHEEL
rescrap-0.1.2.dist-info/METADATA
rescrap-0.1.2.dist-info/RECORD
